x_api_rs/__init__.py
x_api_rs/dm/__init__.py
x_api_rs/fingerprint/__init__.py
x_api_rs/inbox/__init__.py
x_api_rs/posts/__init__.py
x_api_rs/upload/__init__.py
x_api_rs/user/__init__.py
x_api_rs/x_api_rs.abi3.so
x_api_rs/x_api_rs.pyi
x_api_rs-1.0.5.dev0.dist-info/METADATA
x_api_rs-1.0.5.dev0.dist-info/WHEEL
x_api_rs-1.0.5.dev0.dist-info/RECORD
