Metadata-Version: 2.4
Name: x-api-rs
Version: 1.0.5.dev0
Classifier: Programming Language :: Rust
Classifier: Programming Language :: Python :: 3
Classifier: Programming Language :: Python :: 3.8
Classifier: Programming Language :: Python :: 3.9
Classifier: Programming Language :: Python :: 3.10
Classifier: Programming Language :: Python :: 3.11
Classifier: Programming Language :: Python :: 3.12
Classifier: Programming Language :: Python :: 3.13
Classifier: License :: OSI Approved :: MIT License
Classifier: Operating System :: OS Independent
Requires-Dist: pytest>=7.0 ; extra == 'test'
Requires-Dist: pytest-asyncio>=0.21 ; extra == 'test'
Provides-Extra: test
Summary: Twitter/X API 客户端库 (Rust 实现, 提供 Python 绑定)
Author-email: robin <robin528919@gmail.com>
Requires-Python: >=3.8
Project-URL: Documentation, https://x-api-rs.es007.com
Project-URL: Homepage, https://github.com/Robin528919/x-api-rs
Project-URL: Issues, https://github.com/Robin528919/x-api-rs/issues
Project-URL: Repository, https://github.com/Robin528919/x-api-rs.git
